branchtree/__init__.py
branchtree/__main__.py
branchtree/cli.py
branchtree/git.py
branchtree/tree.py
branchtree-0.1.7.dist-info/licenses/LICENSE
branchtree-0.1.7.dist-info/METADATA
branchtree-0.1.7.dist-info/WHEEL
branchtree-0.1.7.dist-info/entry_points.txt
branchtree-0.1.7.dist-info/top_level.txt
branchtree-0.1.7.dist-info/RECORD
