Metadata-Version: 2.4
Name: branchtree
Version: 0.1.7
Project-URL: Homepage, https://github.com/nazsolti/branchtree
Classifier: Development Status :: 3 - Alpha
Classifier: Intended Audience :: Developers
Classifier: License :: OSI Approved :: MIT License
Classifier: Operating System :: OS Independent
Classifier: Programming Language :: Python :: 3
Classifier: Topic :: Software Development :: Version Control :: Git
Requires-Python: >=3.11
License-File: LICENSE
Provides-Extra: dev
Requires-Dist: black>=25.1.0; extra == "dev"
Requires-Dist: build>=1.2.2; extra == "dev"
Requires-Dist: taskipy>=1.14.1; extra == "dev"
Requires-Dist: twine>=6.1.0; extra == "dev"
Dynamic: license-file
